ttls/__init__.py
ttls/cli.py
ttls/client.py
ttls/colours.py
ttls-1.10.0.dist-info/METADATA
ttls-1.10.0.dist-info/WHEEL
ttls-1.10.0.dist-info/entry_points.txt
ttls-1.10.0.dist-info/licenses/LICENSE
ttls-1.10.0.dist-info/RECORD
