Metadata-Version: 2.4
Name: ttls
Version: 1.10.0
Summary: Twinkly Twinkly Little Star
Project-URL: repository, https://github.com/jschlyter/ttls
Author-email: Jakob Schlyter <jakob@schlyter.se>
License-Expression: BSD-2-Clause
License-File: LICENSE
Requires-Python: <4.0,>=3.11
Requires-Dist: aiohttp>=3.11.14
